lgtd/__init__.py
lgtd/decomposition/__init__.py
lgtd/decomposition/lgtd.py
lgtd/decomposition/local_trend.py
lgtd/decomposition/seasonal.py
lgtd/decomposition/utils.py
lgtd/evaluation/__init__.py
lgtd/evaluation/metrics.py
lgtd/evaluation/visualization.py
lgtd-0.1.0.dist-info/METADATA
lgtd-0.1.0.dist-info/WHEEL
lgtd-0.1.0.dist-info/top_level.txt
lgtd-0.1.0.dist-info/RECORD
