Metadata-Version: 2.4
Name: lgtd
Version: 0.1.0
Summary: Local Global Trend Decomposition for Time Series Analysis
Author-email: Chotanansub Sophaken <chotanansub.s@gmail.com>
License: MIT
Project-URL: Homepage, https://github.com/chotanansub/lgtd
Project-URL: Documentation, https://github.com/chotanansub/lgtd/docs/README.md
Project-URL: Repository, https://github.com/chotanansub/lgtd
Keywords: time-series,decomposition,trend,seasonality
Classifier: Development Status :: 3 - Alpha
Classifier: Intended Audience :: Science/Research
Classifier: Topic :: Scientific/Engineering :: Mathematics
Classifier: License :: OSI Approved :: MIT License
Classifier: Programming Language :: Python :: 3
Classifier: Programming Language :: Python :: 3.8
Classifier: Programming Language :: Python :: 3.9
Classifier: Programming Language :: Python :: 3.10
Classifier: Programming Language :: Python :: 3.11
Requires-Python: >=3.8
Requires-Dist: numpy>=1.21.0
Requires-Dist: pandas>=1.3.0
Requires-Dist: scipy>=1.7.0
Requires-Dist: scikit-learn>=1.0.0
Requires-Dist: matplotlib>=3.4.0
Requires-Dist: seaborn>=0.11.0
Requires-Dist: pyyaml>=5.4.0
Requires-Dist: autotrend>=0.2.4
Provides-Extra: experiments
Requires-Dist: statsmodels>=0.13.0; extra == "experiments"
Requires-Dist: stldecompose>=0.0.5; extra == "experiments"
Requires-Dist: jupyter>=1.0.0; extra == "experiments"
Requires-Dist: ipykernel>=6.0.0; extra == "experiments"
Requires-Dist: notebook; extra == "experiments"
Provides-Extra: dev
Requires-Dist: pytest>=7.0.0; extra == "dev"
Requires-Dist: pytest-cov>=3.0.0; extra == "dev"
Requires-Dist: black>=22.0.0; extra == "dev"
Requires-Dist: flake8>=4.0.0; extra == "dev"
Provides-Extra: all
Requires-Dist: lgtd[dev,experiments]; extra == "all"
Dynamic: requires-python
